LICENSE
README.md
setup.cfg
setup.py
lasertools_pulsemodel/__init__.py
lasertools_pulsemodel/pulse_model.py
lasertools_pulsemodel.egg-info/PKG-INFO
lasertools_pulsemodel.egg-info/SOURCES.txt
lasertools_pulsemodel.egg-info/dependency_links.txt
lasertools_pulsemodel.egg-info/requires.txt
lasertools_pulsemodel.egg-info/top_level.txt
lasertools_pulsemodel/model_amplitude/__init__.py
lasertools_pulsemodel/model_amplitude/arbitrary_frequency.py
lasertools_pulsemodel/model_amplitude/arbitrary_wavelength.py
lasertools_pulsemodel/model_amplitude/base.py
lasertools_pulsemodel/model_amplitude/gaussian.py
lasertools_pulsemodel/model_phase/__init__.py
lasertools_pulsemodel/model_phase/arbitrary_frequency.py
lasertools_pulsemodel/model_phase/arbitrary_wavelength.py
lasertools_pulsemodel/model_phase/base.py
lasertools_pulsemodel/model_phase/polynomial.py